{
 "nodes_blueprint": {
  "node_count": "4",
  "node_prefix": "node",
  "node_ui_width": "100",
  "node_ui_height": "50"
 },
 "frame_blueprint": {
  "width": "1000",
  "height": "2000"
 },
 "node0": {
  "max_cache_size": "4",
  "max_payload_size": "100",
  "payload": {
   "temprature_at_bangalore": "25c",
   "pm": "modi",
   "cm": "bommai",
   "avenger": "hulk"
  },
  "cached": {
   "fastestcar": "koinseg agera",
   "richesht_man": "elon musk",
   "second_richest_company":"amazon"
  },
  "type": "Random_CRP",
  "egress": {
   "node1": "5ms",
   "node2": "1ms"
  }
 },
 "node1": {
  "max_cache_size": "3",
  "max_payload_size": "100",
  "type": "Random_CRP",
  "egress": {
   "node3": "1ms"
  },
  "payload": {
   "pm": "modi",
   "cm": "bommai",
   "avenger": "hulk"
  },
  "cached": {
   "temprature_at_bangalore": "10c",
   "great_wall_of_chaina" : "chaina",
   "largest_scrapper" : "burj kalifa",
   "largest_country" : "russia",
   "smallest_country" : "veticoncity"
  }
 },
 "node3": {
  "type": "Random_CRP",
  "max_cache_size" : "3",
  "egress": {
    "node0" : "1ms"
  }
 },
 "node2": {
  "cached": {
   "health_of_node5": "85/100",
   "bugati":"veryon",
   "uvce_location":"bangalore",
   "ping":"pong",
   "king_opposite":"queen"
  },
  "type": "Random_CRP",
  "egress": {
   "node3": "3ms",
   "node1": "7ms"
  }
 }
}
